LICENCE
MANIFEST.in
README.rst
eplist.py
fabfile.py
requirements.txt
setup.py
eplist/__init__.py
eplist/cache.py
eplist/constants.py
eplist/episode.py
eplist/logger.py
eplist/main.py
eplist/poll_sources.py
eplist/settings.py
eplist/show_finder.py
eplist/utils.py
eplist.egg-info/PKG-INFO
eplist.egg-info/SOURCES.txt
eplist.egg-info/dependency_links.txt
eplist.egg-info/entry_points.txt
eplist.egg-info/not-zip-safe
eplist.egg-info/top_level.txt
eplist/gui/__init__.py
eplist/gui/gui.py
eplist/web_sources/__init__.py
eplist/web_sources/anidb.py
eplist/web_sources/epguides.py
eplist/web_sources/tvdb.py
tests/__init__.py
tests/test_anidb.py
tests/test_cache.py
tests/test_parser.py
tests/test_poll_sources.py
tests/test_utils.py