Metadata-Version: 1.1
Name: eplist
Version: 0.1.7
Summary: Simple episode renaming program
Home-page: https://github.com/djt5019/episode_renamer
Author: Dan Tracy
Author-email: djt5019 at gmail dot com
License: unlicense
Platform: all
Classifier: Programming Language :: Python :: 2.7
Classifier: Topic :: Multimedia :: Video
Classifier: Topic :: Utilities
Classifier: Environment :: Console
Classifier: Environment :: X11 Applications :: Qt
Classifier: Operating System :: OS Independent
Requires: BeautifulSoup (>=3.2.0)
Requires: requests (>=0.9.1)
